{
    "Тейсті Джуніор": {
        "link": "/ua/uk-ua/product/200428.html",
        "name": "Тейсті Джуніор",
        "description": "Класика, яку обожнюєш, у зручному форматі для швидкого перекусу. Пухкенька булочка із соковитою яловичою котлетою, сиром ементаль, свіжим салатом, томатом і цибулькою — і все це з легендарним соусом «Біг Тейсті».",
        "Калорійність": "400 ккал/kcal,  Калорійність (20 % DV) ",
        "Жири": "24г/g,  Жири (36 % DV) ",
        "Вуглеводи": "29г/g,  Вуглеводи (11 % DV) ",
        "Білки": "16г/g,  Білки (21 % DV) ",
        "НЖК": "8г/g (36 % DV) N/Aг/g per100g ",
        "Цукор": "6г/g (6 % DV) N/Aг/g per100g ",
        "Сіль": "1.9г/g (38 % DV) N/Aг/g per100g ",
        "Порція": "145г/g (N/A % DV) N/Aг/g per100g "
    },
    "Біг Тейсті® Сингл": {
        "link": "/ua/uk-ua/product/200429.html",
        "name": "Біг Тейсті® Сингл",
        "description": "Він один, але в ньому все, що ти так любиш: соковита котлета з яловичини, два шматочки сиру ементаль і томату, свіжий салат, цибулька й наш культовий соус «Біг Тейсті» в рум’яній булочці з кунжутом.",
        "Калорійність": "620 ккал/kcal,  Калорійність (31 % DV) ",
        "Жири": "40г/g,  Жири (60 % DV) ",
        "Вуглеводи": "38г/g,  Вуглеводи (14 % DV) ",
        "Білки": "26г/g,  Білки (35 % DV) ",
        "НЖК": "14г/g (64 % DV) N/Aг/g per100g ",
        "Цукор": "8г/g (8 % DV) N/Aг/g per100g ",
        "Сіль": "2.9г/g (58 % DV) N/Aг/g per100g ",
        "Порція": "245г/g (N/A % DV) N/Aг/g per100g "
    },
    "Дабл Біг Тейсті®": {
        "link": "/ua/uk-ua/product/200430.html",
        "name": "Дабл Біг Тейсті®",
        "description": "Великий. Соковитий. Новенький Дабл Біг Тейсті®. Дві апетитні яловичі котлети, потрійна порція ніжного сиру, свіжі томати та салат, цибулька й фірмовий соус «Біг Тейсті» в рум’яній булочці з кунжутом. Для тих випадків, коли дууууже хочеться їсти.",
        "Калорійність": "880 ккал/kcal,  Калорійність (44 % DV) ",
        "Жири": "60г/g,  Жири (90 % DV) ",
        "Вуглеводи": "40г/g,  Вуглеводи (15 % DV) ",
        "Білки": "44г/g,  Білки (59 % DV) ",
        "НЖК": "23г/g (105 % DV) N/Aг/g per100g ",
        "Цукор": "8г/g (8 % DV) N/Aг/g per100g ",
        "Сіль": "4.1г/g (82 % DV) N/Aг/g per100g ",
        "Порція": "335г/g (N/A % DV) N/Aг/g per100g "
    },
    "МакКріспі": {
        "link": "/ua/uk-ua/product/200396.html",
        "name": "МакКріспі",
        "description": "Соковите куряче філе в хрусткій паніровці у поєднанні зі свіжим салатом та соусом із зернами гірчиці у пухкенькій булочці. Тобі сподобається!",
        "Калорійність": "490 ккал/kcal,  Калорійність (22 % DV) ",
        "Жири": "16г/g,  Жири (21 % DV) ",
        "Вуглеводи": "57г/g,  Вуглеводи (18 % DV) ",
        "Білки": "28г/g,  Білки (37 % DV) ",
        "НЖК": "2г/g (9 % DV) N/Aг/g per100g ",
        "Цукор": "13г/g (15 % DV) N/Aг/g per100g ",
        "Сіль": "2.4г/g (42 % DV) N/Aг/g per100g ",
        "Порція": "195г/g (N/A % DV) N/Aг/g per100g "
    },
    "МакКріспі Делюкс": {
        "link": "/ua/uk-ua/product/200403.html",
        "name": "МакКріспі Делюкс",
        "description": "Що робить новий МакКріспі Делюкс ще соковитішим? Поєднання курячого філе у хрусткій паніровці зі свіжим салатом, сиром чедер, томатом та свіжим огірочком, що доповнені пікантним соусом із зернами гірчиці у пухкій булочці.",
        "Калорійність": "550 ккал/kcal,  Калорійність (28 % DV) ",
        "Жири": "20г/g,  Жири (31 % DV) ",
        "Вуглеводи": "59г/g,  Вуглеводи (20 % DV) ",
        "Білки": "31г/g,  Білки (47 % DV) ",
        "НЖК": "4г/g (23 % DV) N/Aг/g per100g ",
        "Цукор": "15г/g (16 % DV) N/Aг/g per100g ",
        "Сіль": "2.9г/g (54 % DV) N/Aг/g per100g ",
        "Порція": "240г/g (N/A % DV) N/Aг/g per100g "
    },
    "Біг Мак®": {
        "link": "/ua/uk-ua/product/200148.html",
        "name": "Біг Мак®",
        "description": "Два біфштекси з натуральної яловичини, цибуля, маринований огірок, сир “Чеддер”, свіжий салат, заправлені спеціальним соусом, у булочці з насінням сезаму.",
        "Калорійність": "526 ккал/kcal,  Калорійність (26 % DV) ",
        "Жири": "27г/g,  Жири (39 % DV) ",
        "Вуглеводи": "43г/g,  Вуглеводи (17 % DV) ",
        "Білки": "27г/g,  Білки (54 % DV) ",
        "НЖК": "10г/g (50 % DV)",
        "Цукор": "8.9г/g (10 % DV)",
        "Сіль": "2.2г/g (37 % DV)",
        "Порція": "212г/g "
    },
    "Гамбургер": {
        "link": "/ua/uk-ua/product/200154.html",
        "name": "Гамбургер",
        "description": "Біфштекс із натуральної яловичини, цибуля,\nшматочок маринованого огірка, заправлені\nгірчицею і кетчупом, у запашній булочці з\nпшеничного борошна.",
        "Калорійність": "249 ккал/kcal,  Калорійність (12 % DV) ",
        "Жири": "8.7г/g,  Жири (12 % DV) ",
        "Вуглеводи": "29г/g,  Вуглеводи (11 % DV) ",
        "Білки": "13г/g,  Білки (26 % DV) ",
        "НЖК": "3.5г/g (17 % DV)",
        "Цукор": "7.2г/g (8 % DV)",
        "Сіль": "1.1г/g (18 % DV)",
        "Порція": "96г/g "
    },
    "Чізбургер": {
        "link": "/ua/uk-ua/product/200150.html",
        "name": "Чізбургер",
        "description": "Біфштекс із натуральної яловичини, шматочок сиру “Чеддер”, шматочок маринованого огірка та цибуля, заправлені гірчицею і кетчупом, у булочці з пшеничного борошна.",
        "Калорійність": "298 ккал/kcal,  Калорійність (15 % DV) ",
        "Жири": "13г/g,  Жири (19 % DV) ",
        "Вуглеводи": "29г/g,  Вуглеводи (11 % DV) ",
        "Білки": "16г/g,  Білки (32 % DV) ",
        "НЖК": "6.1г/g (31 % DV)",
        "Цукор": "7.6г/g (8 % DV)",
        "Сіль": "1.6г/g (27 % DV)",
        "Порція": "108г/g (N/A % DV) N/Aг/g per100g "
    },
    "Дабл Чізбургер": {
        "link": "/ua/uk-ua/product/200152.html",
        "name": "Дабл Чізбургер",
        "description": "Два біфштекси з натуральної яловичини, два шматочки сиру «Чедер», два мариновані огірки, цибуля, гірчиця, кетчуп, булочка.",
        "Калорійність": "475 ккал/kcal,  Калорійність (24 % DV) ",
        "Жири": "27.3г/g,  Жири (39 % DV) ",
        "Вуглеводи": "31.1г/g,  Вуглеводи (12 % DV) ",
        "Білки": "26.5г/g,  Білки (53 % DV) ",
        "НЖК": "12.6г/g (59 % DV)",
        "Цукор": "6.5г/g (7 % DV)",
        "Сіль": "2.5г/g (42 % DV)",
        "Порція": "163г/g "
    },
    "МакЧікен®": {
        "link": "/ua/uk-ua/product/200155.html",
        "name": "МакЧікен®",
        "description": "Класичний смак, простий вибір. Хрустка куряча котлета із соковитим салатом і ніжним соусом. Ну як тут відмовитись?!",
        "Калорійність": "448 ккал/kcal,  Калорійність (22 % DV) ",
        "Жири": "18г/g,  Жири (26 % DV) ",
        "Вуглеводи": "49.4г/g,  Вуглеводи (19 % DV) ",
        "Білки": "22.3г/g,  Білки (45 % DV) ",
        "НЖК": "1.9г/g (9 % DV)",
        "Цукор": "5.3г/g (5 % DV)",
        "Сіль": "2.2г/g (37 % DV)",
        "Порція": "180г/g "
    },
    "Філе-о-Фіш®": {
        "link": "/ua/uk-ua/product/200153.html",
        "name": "Філе-о-Фіш®",
        "description": "Ніжне рибне філе із тріскових риб, засмажене у хрумкому паніруванні, півшматочка сиру “Чеддер”, заправлені пікантним соусом, у пухкій булочці з пшеничного борошна.",
        "Калорійність": "327 ккал/kcal,  Калорійність (16 % DV) ",
        "Жири": "14г/g,  Жири (20 % DV) ",
        "Вуглеводи": "35г/g,  Вуглеводи (13 % DV) ",
        "Білки": "15г/g,  Білки (30 % DV) ",
        "НЖК": "2.7г/g (13 % DV)",
        "Цукор": "5.5г/g (6 % DV)",
        "Сіль": "1.4г/g (23 % DV)",
        "Порція": "130г/g "
    },
    "Роял Чізбургер": {
        "link": "/ua/uk-ua/product/200257.html",
        "name": "Роял Чізбургер",
        "description": "Біфштекс із натуральної яловичини, два слайси сиру «Чедер», два шматочки маринованого огірка та свіжа цибуля, заправлені гірчицею та кетчупом, у булочці з пшеничного борошна.",
        "Калорійність": "530 ккал/kcal,  Калорійність (27 % DV) ",
        "Жири": "27г/g,  Жири (39 % DV) ",
        "Вуглеводи": "38г/g,  Вуглеводи (15 % DV) ",
        "Білки": "32г/g,  Білки (64 % DV) ",
        "НЖК": "14г/g (68 % DV)",
        "Цукор": "11г/g (12 % DV)",
        "Сіль": "2.6г/g (43 % DV)",
        "Порція": "194г/g (N/A % DV) N/Aг/g per100g "
    },
    "Дабл Роял Чізбургер": {
        "link": "/ua/uk-ua/product/200266.html",
        "name": "Дабл Роял Чізбургер",
        "description": "Два біфштекси з натуральної яловичини в поєднанні з двома слайсами ніжного сиру «Чедер», двома огірочками та свіжою цибулькою, заправлені гірчицею та кетчупом, у булочці з пшеничного борошна.",
        "Калорійність": "760 ккал/kcal,  Калорійність (38 % DV) ",
        "Жири": "44г/g,  Жири (63 % DV) ",
        "Вуглеводи": "38г/g,  Вуглеводи (15 % DV) ",
        "Білки": "52г/g,  Білки (104 % DV) ",
        "НЖК": "21г/g (107 % DV)",
        "Цукор": "11г/g (12 % DV)",
        "Сіль": "3.0г/g (50 % DV)",
        "Порція": "272г/g (N/A % DV) N/Aг/g per100g "
    },
    "Чізбургер з беконом": {
        "link": "/ua/uk-ua/product/200151.html",
        "name": "Чізбургер з беконом",
        "description": "Соковитий біфштекс із яловичини, доповнений хрумким беконом і маринованим огірком, у поєднанні зі шматочком сиру «Чедер» та цибулею — усе це заправлено гірчицею та кетчупом у запашній булочці із пшеничного борошна.",
        "Калорійність": "0,  Калорійність (0 % DV) ",
        "Жири": "0,  Жири (0 % DV) ",
        "Вуглеводи": "0,  Вуглеводи (0 % DV) ",
        "Білки": "0,  Білки (0 % DV) "
    },
    "Чікен Джуніор": {
        "link": "/ua/uk-ua/product/200372.html",
        "name": "Чікен Джуніор",
        "description": "Соковита куряча котлета із хрусткими шматочками огірочка під «Медово-гірчичним» соусом у запашній булочці з пшеничного борошна.",
        "Калорійність": "0,  Калорійність (0 % DV) ",
        "Жири": "0,  Жири (0 % DV) ",
        "Вуглеводи": "0,  Вуглеводи (0 % DV) ",
        "Білки": "0,  Білки (0 % DV) "
    },
    "Тост із сиром": {
        "link": "/ua/uk-ua/product/200010.html",
        "name": "Тост із сиром",
        "description": "М’яка тепла булочка з двома скибочками сиру чедер.",
        "Калорійність": "245 ккал/kcal,  Калорійність (12 % DV) ",
        "Жири": "10.1г/g,  Жири (15 % DV) ",
        "Вуглеводи": "28г/g,  Вуглеводи (10 % DV) ",
        "Білки": "10.4г/g,  Білки (13 % DV) ",
        "НЖК": "5г/g (23 % DV) N/Aг/g per100g ",
        "Цукор": "5г/g (5 % DV) N/Aг/g per100g ",
        "Сіль": "1.2г/g (24 % DV) N/Aг/g per100g ",
        "Порція": "73г/g (N/A % DV) N/Aг/g per100g "
    },
    "Чікен Рол": {
        "link": "/ua/uk-ua/product/200136.html",
        "name": "Чікен Рол",
        "description": "Загорнуті в тонкий лаваш шматочки курятини, свіжі помідори та хрумкий салат- латук – і все це заправлене пікантним гірчично-медовим соусом.",
        "Калорійність": "340 ккал/kcal,  Калорійність (17 % DV) ",
        "Жири": "10.1г/g,  Жири (15 % DV) ",
        "Вуглеводи": "42.2г/g,  Вуглеводи (15 % DV) ",
        "Білки": "19.2г/g,  Білки (25 % DV) ",
        "НЖК": "2.0г/g (9 % DV)",
        "Цукор": "3.7г/g (4 % DV)",
        "Сіль": "2.2г/g (44 % DV)",
        "Порція": "215г/g "
    },
    "Фіш Рол": {
        "link": "/ua/uk-ua/product/200137.html",
        "name": "Фіш Рол",
        "description": "Свіжий смак овочів у поєднанні з соковитим філе риби в паніруванні. Страва для справжніх гурманів!",
        "Калорійність": "436 ккал/kcal,  Калорійність (22 % DV) ",
        "Жири": "19г/g,  Жири (28 % DV) ",
        "Вуглеводи": "46г/g,  Вуглеводи (18 % DV) ",
        "Білки": "18г/g,  Білки (36 % DV) ",
        "НЖК": "3.34г/g (17 % DV)",
        "Цукор": "3.93г/g (4 % DV)",
        "Сіль": "1.4г/g (24 % DV)",
        "Порція": "190г/g "
    },
    "Чікен МакНагетс®, 4 шт.": {
        "link": "/ua/uk-ua/product/200026.html",
        "name": "Чікен МакНагетс®, 4 шт.",
        "description": "Шматочки ніжного курячого філе, засмажені в хрумкій паніровці.",
        "Калорійність": "176 ккал/kcal,  Калорійність (9 % DV) ",
        "Жири": "8.6г/g,  Жири (12 % DV) ",
        "Вуглеводи": "13г/g,  Вуглеводи (5 % DV) ",
        "Білки": "11г/g,  Білки (22 % DV) ",
        "НЖК": "1.0г/g (5 % DV) N/Aг/g per100g ",
        "Цукор": "0.5г/g (1 % DV) N/Aг/g per100g ",
        "Сіль": "0.8г/g (14 % DV) N/Aг/g per100g ",
        "Порція": "68г/g (N/A % DV) N/Aг/g per100g "
    },
    "Чікен МакНагетс®, 6 шт.": {
        "link": "/ua/uk-ua/product/200027.html",
        "name": "Чікен МакНагетс®, 6 шт.",
        "description": "Апетитні шматочки ніжного курячого філе, засмажені у хрумкій паніровці.",
        "Калорійність": "265 ккал/kcal,  Калорійність (13 % DV) ",
        "Жири": "13г/g,  Жири (18 % DV) ",
        "Вуглеводи": "20г/g,  Вуглеводи (8 % DV) ",
        "Білки": "17г/g,  Білки (33 % DV) ",
        "НЖК": "1.6г/g (8 % DV)",
        "Цукор": "0.7г/g (1 % DV)",
        "Сіль": "1.2г/g (21 % DV)",
        "Порція": "100г/g "
    },
    "Чікен МакНагетс®, 9 шт.": {
        "link": "/ua/uk-ua/product/200028.html",
        "name": "Чікен МакНагетс®, 9 шт.",
        "description": "Апетитні шматочки ніжного курячого філе, засмажені у хрумкій паніровці.",
        "Калорійність": "397 ккал/kcal,  Калорійність (20 % DV) ",
        "Жири": "19г/g,  Жири (28 % DV) ",
        "Вуглеводи": "30г/g,  Вуглеводи (12 % DV) ",
        "Білки": "25г/g,  Білки (50 % DV) ",
        "НЖК": "2.4г/g (12 % DV)",
        "Цукор": "1.1г/g (1 % DV)",
        "Сіль": "1.8г/g (31 % DV)",
        "Порція": "150г/g "
    },
    "Чікен МакНагетс®, 20 шт.": {
        "link": "/ua/uk-ua/product/2133.html",
        "name": "Чікен МакНагетс®, 20 шт.",
        "description": "Апетитні шматочки ніжного курячого філе, засмажені у хрумкій паніровці.",
        "Калорійність": "882 ккал/kcal,  Калорійність (44 % DV) ",
        "Жири": "43г/g,  Жири (61 % DV) ",
        "Вуглеводи": "67г/g,  Вуглеводи (26 % DV) ",
        "Білки": "55г/g,  Білки (110 % DV) ",
        "НЖК": "5.2г/g (26 % DV) N/Aг/g per100g ",
        "Цукор": "2.4г/g (3 % DV) N/Aг/g per100g ",
        "Сіль": "4.1г/g (68 % DV) N/Aг/g per100g ",
        "Порція": "340г/g (N/A % DV) N/Aг/g per100g "
    },
    "Курячі стріпси, 3 шт.": {
        "link": "/ua/uk-ua/product/200339.html",
        "name": "Курячі стріпси, 3 шт.",
        "description": "Смужки білого соковитого курячого філе, що обсмажуються у хрусткій паніровці. Скільки тобі шматочків? Три, щоб з’їсти одному, чи шість для себе і друга або ж дванадцять на велику компанію?",
        "Калорійність": "200 ккал/kcal,  Калорійність (10 % DV) ",
        "Жири": "9.7г/g,  Жири (14 % DV) ",
        "Вуглеводи": "10.1г/g,  Вуглеводи (4 % DV) ",
        "Білки": "18.2г/g,  Білки (36 % DV) ",
        "НЖК": "1.5г/g (7 % DV)",
        "Цукор": "1.1г/g (1 % DV)",
        "Сіль": "1.4г/g (23 % DV)",
        "Порція": "80г/g (N/A % DV) N/Aг/g per100g "
    },
    "Курячі стріпси, 6 шт.": {
        "link": "/ua/uk-ua/product/200340.html",
        "name": "Курячі стріпси, 6 шт.",
        "description": "Смужки білого соковитого курячого філе, що обсмажуються у хрусткій паніровці. Скільки тобі шматочків? Три, щоб з’їсти одному, чи шість для себе і друга або ж дванадцять на велику компанію?",
        "Калорійність": "400 ккал/kcal,  Калорійність (20 % DV) ",
        "Жири": "19.3г/g,  Жири (28 % DV) ",
        "Вуглеводи": "20.2г/g,  Вуглеводи (8 % DV) ",
        "Білки": "36.3г/g,  Білки (73 % DV) ",
        "НЖК": "2.9г/g (15 % DV)",
        "Цукор": "2.1г/g (2 % DV)",
        "Сіль": "2.7г/g (45 % DV)",
        "Порція": "160г/g (N/A % DV) N/Aг/g per100g "
    },
    "Курячі стріпси, 12 шт.": {
        "link": "/ua/uk-ua/product/200341.html",
        "name": "Курячі стріпси, 12 шт.",
        "description": "Смужки білого соковитого курячого філе, що обсмажуються у хрусткій паніровці. Скільки тобі шматочків? Три, щоб з’їсти одному, чи шість для себе і друга або ж дванадцять на велику компанію?",
        "Калорійність": "800 ккал/kcal,  Калорійність (40 % DV) ",
        "Жири": "38.6г/g,  Жири (55 % DV) ",
        "Вуглеводи": "40.3г/g,  Вуглеводи (16 % DV) ",
        "Білки": "72.7г/g,  Білки (145 % DV) ",
        "НЖК": "5.9г/g (29 % DV)",
        "Цукор": "4.2г/g (5 % DV)",
        "Сіль": "5.5г/g (92 % DV)",
        "Порція": "320г/g (N/A % DV) N/Aг/g per100g "
    },
    "Чікен Бокс": {
        "link": "/ua/uk-ua/product/200342.html",
        "name": "Чікен Бокс",
        "description": "Мікс Бокс для невеличкої компанії друзів. Адже всередині знайдеш дев’ять золотавих Чікен МакНагетс® та шість стріпсів із курячого філе.",
        "Калорійність": "831 ккал/kcal,  Калорійність (42 % DV) ",
        "Жири": "39.2г/g,  Жири (56 % DV) ",
        "Вуглеводи": "55.1г/g,  Вуглеводи (21 % DV) ",
        "Білки": "64.5г/g,  Білки (129 % DV) ",
        "НЖК": "5.3г/g (27 % DV)",
        "Цукор": "3.4г/g (4 % DV)",
        "Сіль": "4.9г/g (82 % DV)",
        "Порція": "330г/g (N/A % DV) N/Aг/g per100g "
    },
    "Картопля Фрі велика": {
        "link": "/ua/uk-ua/product/200051.html",
        "name": "Картопля Фрі велика",
        "description": "Добірна картопля, засмажена в натуральній олії і трохи підсолена.",
        "Калорійність": "0,  Калорійність (0 % DV) ",
        "Жири": "0,  Жири (0 % DV) ",
        "Вуглеводи": "0,  Вуглеводи (0 % DV) ",
        "Білки": "0,  Білки (0 % DV) "
    },
    "Картопля Фрі середня": {
        "link": "/ua/uk-ua/product/200052.html",
        "name": "Картопля Фрі середня",
        "description": "Добірна картопля, засмажена в натуральній олії і трохи підсолена.",
        "Калорійність": "330 ккал/kcal,  Калорійність (16 % DV) ",
        "Жири": "16г/g,  Жири (22 % DV) ",
        "Вуглеводи": "41г/g,  Вуглеводи (16 % DV) ",
        "Білки": "4г/g,  Білки (8 % DV) ",
        "НЖК": "1.49г/g (7 % DV)",
        "Цукор": "0.407г/g (0 % DV)",
        "Сіль": "0.53г/g (9 % DV)",
        "Порція": "90г/g "
    },
    "Картопля Фрі маленька": {
        "link": "/ua/uk-ua/product/200053.html",
        "name": "Картопля Фрі маленька",
        "description": "Добірна картопля, засмажена в натуральній олії і трохи підсолена.",
        "Калорійність": "231 ккал/kcal,  Калорійність (12 % DV) ",
        "Жири": "11г/g,  Жири (16 % DV) ",
        "Вуглеводи": "29г/g,  Вуглеводи (11 % DV) ",
        "Білки": "2.8г/g,  Білки (6 % DV) ",
        "НЖК": "1г/g (5 % DV)",
        "Цукор": "0.3г/g (0 % DV)",
        "Сіль": "0.55г/g (9 % DV)",
        "Порція": "60г/g "
    },
    "Картопляні діпи": {
        "link": "/ua/uk-ua/product/200195.html",
        "name": "Картопляні діпи",
        "description": "Апетитні скибочки добірної картоплі, засмажені в натуральній олії і трохи підсолені.",
        "Калорійність": "232 ккал/kcal,  Калорійність (12 % DV) ",
        "Жири": "5.7г/g,  Жири (9 % DV) ",
        "Вуглеводи": "40.1г/g,  Вуглеводи (15 % DV) ",
        "Білки": "3.3г/g,  Білки (4 % DV) ",
        "НЖК": "0.6г/g (5 % DV)",
        "Цукор": "0.3г/g (0 % DV)",
        "Сіль": "0.7г/g (14 % DV)",
        "Порція": "150г/g (N/A % DV) N/Aг/g per100g "
    },
    "Соус «Хабанеро»": {
        "link": "/ua/uk-ua/product/200375.html",
        "name": "Соус «Хабанеро»",
        "description": "Пікантний перець Хабанеро, солодка паприка й прянощі. Спробуй із курячими крильцями, стріпсами, Картоплею Фрі або Чікен МакНагетс®!",
        "Калорійність": "120 ккал/kcal,  Калорійність (6 % DV) ",
        "Жири": "12.4г/g,  Жири (18 % DV) ",
        "Вуглеводи": "3.4г/g,  Вуглеводи (1 % DV) ",
        "Білки": "0.3г/g,  Білки (0 % DV) ",
        "НЖК": "1.4г/g (5 % DV)",
        "Цукор": "1.7г/g (2 % DV)",
        "Сіль": "0.18г/g (16 % DV)",
        "Порція": "40г/g (N/A % DV) N/Aг/g per100g "
    },
    "Соус із сиром Дорблю": {
        "link": "/ua/uk-ua/product/200376.html",
        "name": "Соус із сиром Дорблю",
        "description": "Ніжний соус із вишуканим вершковим смаком сиру Дорблю — ідеальне доповнення до хрумких снеків.",
        "Калорійність": "100 ккал/kcal,  Калорійність (5 % DV) ",
        "Жири": "10.4г/g,  Жири (15 % DV) ",
        "Вуглеводи": "2.7г/g,  Вуглеводи (1 % DV) ",
        "Білки": "0.4г/g,  Білки (0 % DV) ",
        "НЖК": "1.2г/g (5 % DV)",
        "Цукор": "1.3г/g (1 % DV)",
        "Сіль": "0.8г/g (16 % DV)",
        "Порція": "40г/g (N/A % DV) N/Aг/g per100g "
    },
    "Майонез": {
        "link": "/ua/uk-ua/product/200144.html",
        "name": "Майонез",
        "description": "",
        "Калорійність": "119 ккал/kcal,  Калорійність (6 % DV) ",
        "Жири": "13г/g,  Жири (18 % DV) ",
        "Вуглеводи": "1.2г/g,  Вуглеводи (0 % DV) ",
        "Білки": "0.1г/g,  Білки (0 % DV) ",
        "НЖК": "0.525г/g (3 % DV) N/Aг/g per100g ",
        "Цукор": "1г/g (1 % DV) N/Aг/g per100g ",
        "Сіль": "0.31г/g (5 % DV)",
        "Порція": "25г/g "
    },
    "Соус «Барбекю»": {
        "link": "/ua/uk-ua/product/200140.html",
        "name": "Соус «Барбекю»",
        "description": "",
        "Калорійність": "0,  Калорійність (0 % DV) ",
        "Жири": "0,  Жири (0 % DV) ",
        "Вуглеводи": "0,  Вуглеводи (0 % DV) ",
        "Білки": "0,  Білки (0 % DV) "
    },
    "Кетчуп": {
        "link": "/ua/uk-ua/product/200143.html",
        "name": "Кетчуп",
        "description": "",
        "Калорійність": "0,  Калорійність (0 % DV) ",
        "Жири": "0,  Жири (0 % DV) ",
        "Вуглеводи": "0,  Вуглеводи (0 % DV) ",
        "Білки": "0,  Білки (0 % DV) "
    },
    "Соус «Гірчичний»": {
        "link": "/ua/uk-ua/product/200145.html",
        "name": "Соус «Гірчичний»",
        "description": "",
        "Калорійність": "55 ккал/kcal,  Калорійність (3 % DV) ",
        "Жири": "3г/g,  Жири (4 % DV) ",
        "Вуглеводи": "6.4г/g,  Вуглеводи (2 % DV) ",
        "Білки": "0.5г/g,  Білки (1 % DV) ",
        "НЖК": "0г/g (0 % DV)",
        "Цукор": "3г/g (0 % DV)",
        "Сіль": "0г/g (0 % DV) N/Aг/g per100g ",
        "Порція": "25г/g (N/A % DV) N/Aг/g per100g "
    },
    "Соус «Кисло-солодкий»": {
        "link": "/ua/uk-ua/product/200146.html",
        "name": "Соус «Кисло-солодкий»",
        "description": "",
        "Калорійність": "41 ккал/kcal,  Калорійність (2 % DV) ",
        "Жири": "0.3г/g,  Жири (0 % DV) ",
        "Вуглеводи": "9.4г/g,  Вуглеводи (4 % DV) ",
        "Білки": "0.1г/g,  Білки (0 % DV) ",
        "НЖК": "0г/g (0 % DV)",
        "Цукор": "3г/g (0 % DV)",
        "Сіль": "0.00г/g (0 % DV)",
        "Порція": "25г/g "
    },
    "Соус «Сирний»": {
        "link": "/ua/uk-ua/product/200141.html",
        "name": "Соус «Сирний»",
        "description": "",
        "Калорійність": "0,  Калорійність (0 % DV) ",
        "Жири": "0,  Жири (0 % DV) ",
        "Вуглеводи": "0,  Вуглеводи (0 % DV) ",
        "Білки": "0,  Білки (0 % DV) "
    },
    "Мед": {
        "link": "/ua/uk-ua/product/200054.html",
        "name": "Мед",
        "description": "",
        "Калорійність": "0,  Калорійність (0 % DV) ",
        "Жири": "0,  Жири (0 % DV) ",
        "Вуглеводи": "0,  Вуглеводи (0 % DV) ",
        "Білки": "0,  Білки (0 % DV) "
    },
    "МакСанді® Карамель": {
        "link": "/ua/uk-ua/product/200123.html",
        "name": "МакСанді® Карамель",
        "description": "Охолоджена молочна суміш, збита до ідеального морозива та прикрашена карамельною поливою.",
        "Калорійність": "286 ккал/kcal,  Калорійність (14 % DV) ",
        "Жири": "6.1г/g,  Жири (9 % DV) ",
        "Вуглеводи": "53г/g,  Вуглеводи (20 % DV) ",
        "Білки": "4.7г/g,  Білки (9 % DV) ",
        "НЖК": "4.1г/g (20 % DV)",
        "Цукор": "38г/g (42 % DV)",
        "Сіль": "0.28г/g (5 % DV)",
        "Порція": "138г/g "
    },
    "МакСанді® Шоколад": {
        "link": "/ua/uk-ua/product/200125.html",
        "name": "МакСанді® Шоколад",
        "description": "Охолоджена молочна суміш, збита до ідеального морозива та прикрашена шоколадною поливою.",
        "Калорійність": "278 ккал/kcal,  Калорійність (14 % DV) ",
        "Жири": "8.2г/g,  Жири (12 % DV) ",
        "Вуглеводи": "45г/g,  Вуглеводи (17 % DV) ",
        "Білки": "5.5г/g,  Білки (11 % DV) ",
        "НЖК": "6.4г/g (32 % DV)",
        "Цукор": "42г/g (46 % DV)",
        "Сіль": "0.38г/g (6 % DV)",
        "Порція": "138г/g "
    },
    "МакСанді® Полуниця": {
        "link": "/ua/uk-ua/product/200127.html",
        "name": "МакСанді® Полуниця",
        "description": "Охолоджена молочна суміш, збита до ідеального морозива та прикрашена полуничною поливою.",
        "Калорійність": "0,  Калорійність (0 % DV) ",
        "Жири": "0,  Жири (0 % DV) ",
        "Вуглеводи": "0,  Вуглеводи (0 % DV) ",
        "Білки": "0,  Білки (0 % DV) "
    },
    "МакСанді® Карамель у вафельному стаканчику": {
        "link": "/ua/uk-ua/product/200124.html",
        "name": "МакСанді® Карамель у вафельному стаканчику",
        "description": "Охолоджена молочна суміш, збита до ідеального морозива та прикрашена карамельною поливою, у вафельному стаканчику.",
        "Калорійність": "0,  Калорійність (0 % DV) ",
        "Жири": "0,  Жири (0 % DV) ",
        "Вуглеводи": "0,  Вуглеводи (0 % DV) ",
        "Білки": "0,  Білки (0 % DV) "
    },
    "МакСанді® Шоколад у вафельному стаканчику": {
        "link": "/ua/uk-ua/product/200126.html",
        "name": "МакСанді® Шоколад у вафельному стаканчику",
        "description": "Охолоджена молочна суміш, збита до ідеального морозива та прикрашена шоколадною поливою, у вафельному стаканчику.",
        "Калорійність": "0,  Калорійність (0 % DV) ",
        "Жири": "0,  Жири (0 % DV) ",
        "Вуглеводи": "0,  Вуглеводи (0 % DV) ",
        "Білки": "0,  Білки (0 % DV) "
    },
    "МакСанді® Полуниця у вафельному стаканчику": {
        "link": "/ua/uk-ua/product/200128.html",
        "name": "МакСанді® Полуниця у вафельному стаканчику",
        "description": "Охолоджена молочна суміш, збита до ідеального морозива та прикрашена полуничною поливою, у вафельному стаканчику.",
        "Калорійність": "0,  Калорійність (0 % DV) ",
        "Жири": "0,  Жири (0 % DV) ",
        "Вуглеводи": "0,  Вуглеводи (0 % DV) ",
        "Білки": "0,  Білки (0 % DV) "
    },
    "Морозиво Ріжок": {
        "link": "/ua/uk-ua/product/200055.html",
        "name": "Морозиво Ріжок",
        "description": "Морозиво, приготоване з добірної молочної суміші, у хрусткому стаканчику.",
        "Калорійність": "171 ккал/kcal,  Калорійність (9 % DV) ",
        "Жири": "3.95446153г/g,  Жири (6 % DV) ",
        "Вуглеводи": "28.9876923г/g,  Вуглеводи (11 % DV) ",
        "Білки": "4.42557692г/g,  Білки (9 % DV) ",
        "НЖК": "2.20309615г/g (11 % DV)",
        "Цукор": "22.3421538г/g (25 % DV)",
        "Сіль": "0.18940384г/g (3 % DV)",
        "Порція": "95г/g "
    },
    "МакФлурі® Кіт Кат Шоколад": {
        "link": "/ua/uk-ua/product/200112.html",
        "name": "МакФлурі® Кіт Кат Шоколад",
        "description": "Морозиво із шоколадною поливою і КітКат.",
        "Калорійність": "331 ккал/kcal,  Калорійність (17 % DV) ",
        "Жири": "7.93г/g,  Жири (11 % DV) ",
        "Вуглеводи": "56г/g,  Вуглеводи (22 % DV) ",
        "Білки": "8.49г/g,  Білки (17 % DV) ",
        "НЖК": "1.14г/g (6 % DV)",
        "Цукор": "25.52г/g (28 % DV)",
        "Сіль": "0.01г/g (0 % DV)",
        "Порція": "195г/g "
    },
    "МакФлурі® Кіт Кат Карамель": {
        "link": "/ua/uk-ua/product/200111.html",
        "name": "МакФлурі® Кіт Кат Карамель",
        "description": "Морозиво із карамельною поливою і КітКат.",
        "Калорійність": "354 ккал/kcal,  Калорійність (18 % DV) ",
        "Жири": "9г/g,  Жири (13 % DV) ",
        "Вуглеводи": "60г/g,  Вуглеводи (23 % DV) ",
        "Білки": "8.13г/g,  Білки (16 % DV) ",
        "НЖК": "2.02г/g (10 % DV)",
        "Цукор": "37.22г/g (41 % DV)",
        "Сіль": "0.13г/g (2 % DV)",
        "Порція": "195г/g "
    },
    "МакФлурі® Кіт Кат Полуниця": {
        "link": "/ua/uk-ua/product/200113.html",
        "name": "МакФлурі® Кіт Кат Полуниця",
        "description": "Морозиво із полуничною поливою і Кіт Кат.",
        "Калорійність": "318 ккал/kcal,  Калорійність (16 % DV) ",
        "Жири": "7.71г/g,  Жири (11 % DV) ",
        "Вуглеводи": "54г/g,  Вуглеводи (21 % DV) ",
        "Білки": "7.71г/g,  Білки (15 % DV) ",
        "НЖК": "1.14г/g (6 % DV)",
        "Цукор": "39.68г/g (44 % DV)",
        "Сіль": "0.01г/g (0 % DV)",
        "Порція": "195г/g "
    },
    "МакШейк® Шоколад": {
        "link": "/ua/uk-ua/product/200116.html",
        "name": "МакШейк® Шоколад",
        "description": "Чудово збитий коктейль, приготований із добірного молока та шоколадного сиропу.",
        "Калорійність": "0,  Калорійність (0 % DV) ",
        "Жири": "0,  Жири (0 % DV) ",
        "Вуглеводи": "0,  Вуглеводи (0 % DV) ",
        "Білки": "0,  Білки (0 % DV) "
    },
    "МакШейк® Ваніль": {
        "link": "/ua/uk-ua/product/200121.html",
        "name": "МакШейк® Ваніль",
        "description": "Чудово збитий коктейль, приготований із добірного молока та ванільного сиропу.",
        "Калорійність": "0,  Калорійність (0 % DV) ",
        "Жири": "0,  Жири (0 % DV) ",
        "Вуглеводи": "0,  Вуглеводи (0 % DV) ",
        "Білки": "0,  Білки (0 % DV) "
    },
    "МакШейк® Полуниця": {
        "link": "/ua/uk-ua/product/200119.html",
        "name": "МакШейк® Полуниця",
        "description": "Чудово збитий коктейль, приготований із добірного молока та полуничного сиропу.",
        "Калорійність": "415 ккал/kcal,  Калорійність (21 % DV) ",
        "Жири": "7.6г/g,  Жири (11 % DV) ",
        "Вуглеводи": "74г/g,  Вуглеводи (29 % DV) ",
        "Білки": "11г/g,  Білки (22 % DV) ",
        "НЖК": "1.6г/g (8 % DV)",
        "Цукор": "69г/g (76 % DV)",
        "Сіль": "0.32г/g (5 % DV)",
        "Порція": "450мл/ml "
    },
    "МакПиріг® вишневий": {
        "link": "/ua/uk-ua/product/200114.html",
        "name": "МакПиріг® вишневий",
        "description": "Хрумкий, свіжоспечений МакПиріг® із вишневим наповнювачем.",
        "Калорійність": "272 ккал/kcal,  Калорійність (14 % DV) ",
        "Жири": "15г/g,  Жири (21 % DV) ",
        "Вуглеводи": "31г/g,  Вуглеводи (12 % DV) ",
        "Білки": "2.41г/g,  Білки (5 % DV) ",
        "НЖК": "3.152г/g (16 % DV)",
        "Цукор": "11.36г/g (13 % DV)",
        "Сіль": "0.47г/g (8 % DV)",
        "Порція": "80г/g "
    },
    "Круасан мигдалевий": {
        "link": "/ua/uk-ua/product/200249.html",
        "name": "Круасан мигдалевий",
        "description": "",
        "Калорійність": "273 ккал/kcal,  Калорійність (14 % DV) ",
        "Жири": "16г/g,  Жири (23 % DV) ",
        "Вуглеводи": "26г/g,  Вуглеводи (10 % DV) ",
        "Білки": "5г/g,  Білки (10 % DV) ",
        "НЖК": "0г/g (0 % DV)",
        "Цукор": "3.7125г/g (4 % DV)",
        "Сіль": "0.4575г/g (8 % DV)",
        "Порція": "65г/g (N/A % DV) N/Aг/g per100g "
    },
    "Круасан із какао-кремом": {
        "link": "/ua/uk-ua/product/200231.html",
        "name": "Круасан із какао-кремом",
        "description": "Запашний круасан із хрусткою золотою скоринкою та ніжним какао-кремом.",
        "Калорійність": "295 ккал/kcal,  Калорійність (15 % DV) ",
        "Жири": "18г/g,  Жири (26 % DV) ",
        "Вуглеводи": "28г/g,  Вуглеводи (11 % DV) ",
        "Білки": "4.4925г/g,  Білки (9 % DV) ",
        "НЖК": "0г/g (0 % DV)",
        "Цукор": "4.425г/g (5 % DV)",
        "Сіль": "0.45г/g (8 % DV)",
        "Порція": "65г/g (N/A % DV) N/Aг/g per100g "
    },
    "Лате велике": {
        "link": "/ua/uk-ua/product/200041.html",
        "name": "Лате велике",
        "description": "Лате – кавовий напій, який містить молоко. Особливістю цієї кави є те, що, на відміну від капучино, у лате молока значно більше.",
        "Калорійність": "130 ккал/kcal,  Калорійність (6 % DV) ",
        "Жири": "7.0г/g,  Жири (10 % DV) ",
        "Вуглеводи": "10.4г/g,  Вуглеводи (4 % DV) ",
        "Білки": "6.2г/g,  Білки (12 % DV) ",
        "НЖК": "0г/g (0 % DV)",
        "Цукор": "0.0г/g (0 % DV)",
        "Сіль": "0.0г/g (0 % DV)",
        "Порція": "295мл/ml "
    },
    "Лате мале": {
        "link": "/ua/uk-ua/product/200042.html",
        "name": "Лате мале",
        "description": "Лате – кавовий напій, який містить молоко. Особливістю цієї кави є те, що, на відміну від капучино, у лате молока значно більше.",
        "Калорійність": "82 ккал/kcal,  Калорійність (4 % DV) ",
        "Жири": "4.5г/g,  Жири (6 % DV) ",
        "Вуглеводи": "6.6г/g,  Вуглеводи (3 % DV) ",
        "Білки": "3.9г/g,  Білки (8 % DV) ",
        "НЖК": "0.0г/g (0 % DV)",
        "Цукор": "0.0г/g (0 % DV)",
        "Сіль": "0.0г/g (0 % DV)",
        "Порція": "195мл/ml "
    },
    "Капучино велике": {
        "link": "/ua/uk-ua/product/200039.html",
        "name": "Капучино велике",
        "description": "Капучино – це мікс еспресо та гарячого молока у рівних пропорціях. Особливістю цієї кави є смачна молочна пінка, яка утворюється завдяки поєднанню пари та молока.",
        "Калорійність": "0,  Калорійність (0 % DV) ",
        "Жири": "0,  Жири (0 % DV) ",
        "Вуглеводи": "0,  Вуглеводи (0 % DV) ",
        "Білки": "0,  Білки (0 % DV) "
    },
    "Капучино мале": {
        "link": "/ua/uk-ua/product/200040.html",
        "name": "Капучино мале",
        "description": "Капучино – це мікс еспресо та гарячого молока у рівних пропорціях. Особливістю цієї кави є смачна молочна пінка, яка утворюється завдяки поєднанню пари та молока.",
        "Калорійність": "0,  Калорійність (0 % DV) ",
        "Жири": "0,  Жири (0 % DV) ",
        "Вуглеводи": "0,  Вуглеводи (0 % DV) ",
        "Білки": "0,  Білки (0 % DV) "
    },
    "Американо велике": {
        "link": "/ua/uk-ua/product/200036.html",
        "name": "Американо велике",
        "description": "Американо – це еспресо з додаванням гарячої води і тому напій має аналогічні характеристики.",
        "Калорійність": "0,  Калорійність (0 % DV) ",
        "Жири": "0,  Жири (0 % DV) ",
        "Вуглеводи": "0,  Вуглеводи (0 % DV) ",
        "Білки": "0,  Білки (0 % DV) "
    },
    "Американо мале": {
        "link": "/ua/uk-ua/product/200037.html",
        "name": "Американо мале",
        "description": "Американо – це еспресо з додаванням гарячої води і тому напій має аналогічні характеристики.",
        "Калорійність": "0,  Калорійність (0 % DV) ",
        "Жири": "0,  Жири (0 % DV) ",
        "Вуглеводи": "0,  Вуглеводи (0 % DV) ",
        "Білки": "0,  Білки (0 % DV) "
    },
    "Американо з молоком мале": {
        "link": "/ua/uk-ua/product/200243.html",
        "name": "Американо з молоком мале",
        "description": "Американо з молоком – це еспресо з додаванням гарячої води та молока тому напій має м'якший смак, ніж американо.",
        "Калорійність": "0,  Калорійність (0 % DV) ",
        "Жири": "0,  Жири (0 % DV) ",
        "Вуглеводи": "0,  Вуглеводи (0 % DV) ",
        "Білки": "0,  Білки (0 % DV) "
    },
    "Американо з молоком велике": {
        "link": "/ua/uk-ua/product/200244.html",
        "name": "Американо з молоком велике",
        "description": "Американо з молоком – це еспресо з додаванням гарячої води та молока тому напій має м'якший смак, ніж американо.",
        "Калорійність": "0,  Калорійність (0 % DV) ",
        "Жири": "0,  Жири (0 % DV) ",
        "Вуглеводи": "0,  Вуглеводи (0 % DV) ",
        "Білки": "0,  Білки (0 % DV) "
    },
    "Еспресо": {
        "link": "/ua/uk-ua/product/200035.html",
        "name": "Еспресо",
        "description": "Еспресо – дуже міцна кава без молока в маленьких порціях. Еспресо має густу однорідну «живу» пінку світло-горіхового кольору з «тигровими» розводами, яка відновлюється після розмішування напою.",
        "Калорійність": "0,  Калорійність (0 % DV) ",
        "Жири": "0,  Жири (0 % DV) ",
        "Вуглеводи": "0,  Вуглеводи (0 % DV) ",
        "Білки": "0,  Білки (0 % DV) "
    },
    "Подвійне еспресо": {
        "link": "/ua/uk-ua/product/200242.html",
        "name": "Подвійне еспресо",
        "description": "Подвійне еспресо – дуже міцна кава без молока в маленьких порціях. Подвійне еспресо має густу однорідну «живу» пінку світло-горіхового кольору з «тигровими» розводами, яка відновлюється після розмішування напою.",
        "Калорійність": "0,  Калорійність (0 % DV) ",
        "Жири": "0,  Жири (0 % DV) ",
        "Вуглеводи": "0,  Вуглеводи (0 % DV) ",
        "Білки": "0,  Білки (0 % DV) "
    },
    "Флет Вайт": {
        "link": "/ua/uk-ua/product/200044.html",
        "name": "Флет Вайт",
        "description": "Флет Вайт – для тих, хто любить насичений кавовий смак подвійного еспресо з додаванням спіненого гарячого молока. Тепер ще більш насичений смак вашої улюбленої кави.",
        "Калорійність": "65 ккал/kcal,  Калорійність (3 % DV) ",
        "Жири": "3.5г/g,  Жири (5 % DV) ",
        "Вуглеводи": "5.2г/g,  Вуглеводи (2 % DV) ",
        "Білки": "3.1г/g,  Білки (6 % DV) ",
        "НЖК": "0.0г/g (0 % DV) N/Aг/g per100g ",
        "Цукор": "0.0г/g (0 % DV) N/Aг/g per100g ",
        "Сіль": "0.0г/g (0 % DV) N/Aг/g per100g ",
        "Порція": "155мл/ml (N/A % DV) N/Aмл/ml per100g "
    },
    "Какао велике": {
        "link": "/ua/uk-ua/product/200033.html",
        "name": "Какао велике",
        "description": "Гаряче молоко в тандемі з какао подарують м’який смак та чудовий настрій на весь день.",
        "Калорійність": "210 ккал/kcal,  Калорійність (11 % DV) ",
        "Жири": "4.46г/g,  Жири (6 % DV) ",
        "Вуглеводи": "33.65г/g,  Вуглеводи (13 % DV) ",
        "Білки": "8.05г/g,  Білки (16 % DV) ",
        "НЖК": "0.333г/g (2 % DV) N/Aг/g per100g ",
        "Цукор": "25.55г/g (28 % DV) N/Aг/g per100g ",
        "Сіль": "0.315г/g (5 % DV) N/Aг/g per100g ",
        "Порція": "300мл/ml (N/A % DV) N/Aмл/ml per100g "
    },
    "Какао мале": {
        "link": "/ua/uk-ua/product/200034.html",
        "name": "Какао мале",
        "description": "Гаряче молоко в тандемі з какао подарують м’який смак та чудовий настрій на весь день.",
        "Калорійність": "136 ккал/kcal,  Калорійність (7 % DV) ",
        "Жири": "2.48г/g,  Жири (4 % DV) ",
        "Вуглеводи": "22.76г/g,  Вуглеводи (9 % DV) ",
        "Білки": "4.99г/g,  Білки (10 % DV) ",
        "НЖК": "0.238г/g (1 % DV) N/Aг/g per100g ",
        "Цукор": "18.25г/g (20 % DV) N/Aг/g per100g ",
        "Сіль": "0.225г/g (4 % DV) N/Aг/g per100g ",
        "Порція": "200мл/ml (N/A % DV) N/Aмл/ml per100g "
    },
    "Мокко": {
        "link": "/ua/uk-ua/product/200083.html",
        "name": "Мокко",
        "description": "Мокко - солодкий кавовий напій із додаванням молока та ніжного какао.",
        "Калорійність": "165 ккал/kcal,  Калорійність (8 % DV) ",
        "Жири": "7.0г/g,  Жири (10 % DV) ",
        "Вуглеводи": "21.2г/g,  Вуглеводи (8 % DV) ",
        "Білки": "4.4г/g,  Білки (9 % DV) ",
        "НЖК": "3.3г/g (17 % DV) N/Aг/g per100g ",
        "Цукор": "16.7г/g (19 % DV) N/Aг/g per100g ",
        "Сіль": "0.3г/g (4 % DV) N/Aг/g per100g ",
        "Порція": "295мл/ml (N/A % DV) N/Aмл/ml per100g "
    },
    "Чай чорний": {
        "link": "/ua/uk-ua/product/200162.html",
        "name": "Чай чорний",
        "description": "Оригінальний чорний чай.",
        "Калорійність": "0 ккал/kcal,  Калорійність (0 % DV) ",
        "Жири": "0г/g,  Жири (0 % DV) ",
        "Вуглеводи": "0г/g,  Вуглеводи (0 % DV) ",
        "Білки": "0г/g,  Білки (0 % DV) ",
        "НЖК": "0г/g (0 % DV)",
        "Цукор": "0г/g (0 % DV)",
        "Сіль": "0г/g (0 % DV)",
        "Порція": "300мл/ml "
    },
    "Чай зелений із цитрусовими": {
        "link": "/ua/uk-ua/product/200163.html",
        "name": "Чай зелений із цитрусовими",
        "description": "Оригінальний зелений чай.",
        "Калорійність": "0,  Калорійність (0 % DV) ",
        "Жири": "0,  Жири (0 % DV) ",
        "Вуглеводи": "0,  Вуглеводи (0 % DV) ",
        "Білки": "0,  Білки (0 % DV) "
    },
    "Апельсиновий сік великий": {
        "link": "/ua/uk-ua/product/200059.html",
        "name": "Апельсиновий сік великий",
        "description": "Натуральний прохолодний апельсиновий сік без додавання цукру.",
        "Калорійність": "0,  Калорійність (0 % DV) ",
        "Жири": "0,  Жири (0 % DV) ",
        "Вуглеводи": "0,  Вуглеводи (0 % DV) ",
        "Білки": "0,  Білки (0 % DV) "
    },
    "Апельсиновий сік маленький": {
        "link": "/ua/uk-ua/product/200060.html",
        "name": "Апельсиновий сік маленький",
        "description": "Натуральний прохолодний апельсиновий сік без додавання цукру.",
        "Калорійність": "0,  Калорійність (0 % DV) ",
        "Жири": "0,  Жири (0 % DV) ",
        "Вуглеводи": "0,  Вуглеводи (0 % DV) ",
        "Білки": "0,  Білки (0 % DV) "
    },
    "Кока-Кола® велика": {
        "link": "/ua/uk-ua/product/200030.html",
        "name": "Кока-Кола® велика",
        "description": "Всесвітньо відомий освіжаючий напій.",
        "Калорійність": "204 ккал/kcal,  Калорійність (10 % DV) ",
        "Жири": "0г/g,  Жири (0 % DV) ",
        "Вуглеводи": "51г/g,  Вуглеводи (20 % DV) ",
        "Білки": "0г/g,  Білки (0 % DV) ",
        "НЖК": "0г/g (0 % DV) N/Aг/g per100g ",
        "Цукор": "51г/g (57 % DV) N/Aг/g per100g ",
        "Сіль": "0г/g (0 % DV) N/Aг/g per100g ",
        "Порція": "500мл/ml (N/A % DV) N/Aмл/ml per100g "
    },
    "Кока-Кола® середня": {
        "link": "/ua/uk-ua/product/200031.html",
        "name": "Кока-Кола® середня",
        "description": "Всесвітньо відомий освіжаючий напій.",
        "Калорійність": "163 ккал/kcal,  Калорійність (8 % DV) ",
        "Жири": "0г/g,  Жири (0 % DV) ",
        "Вуглеводи": "41г/g,  Вуглеводи (16 % DV) ",
        "Білки": "0г/g,  Білки (0 % DV) ",
        "НЖК": "0г/g (0 % DV) N/Aг/g per100g ",
        "Цукор": "40.8г/g (45 % DV) N/Aг/g per100g ",
        "Сіль": "0г/g (0 % DV) N/Aг/g per100g ",
        "Порція": "400мл/ml (N/A % DV) N/Aмл/ml per100g "
    },
    "Кока-Кола® мала": {
        "link": "/ua/uk-ua/product/200032.html",
        "name": "Кока-Кола® мала",
        "description": "Всесвітньо відомий освіжаючий напій.",
        "Калорійність": "102 ккал/kcal,  Калорійність (5 % DV) ",
        "Жири": "0г/g,  Жири (0 % DV) ",
        "Вуглеводи": "26г/g,  Вуглеводи (10 % DV) ",
        "Білки": "0г/g,  Білки (0 % DV) ",
        "НЖК": "0г/g (0 % DV) N/Aг/g per100g ",
        "Цукор": "25.5г/g (28 % DV) N/Aг/g per100g ",
        "Сіль": "0г/g (0 % DV) N/Aг/g per100g ",
        "Порція": "250мл/ml (N/A % DV) N/Aмл/ml per100g "
    },
    "Фанта® велика": {
        "link": "/ua/uk-ua/product/200048.html",
        "name": "Фанта® велика",
        "description": "Всесвітньо відомий освіжаючий напій.",
        "Калорійність": "0,  Калорійність (0 % DV) ",
        "Жири": "0,  Жири (0 % DV) ",
        "Вуглеводи": "0,  Вуглеводи (0 % DV) ",
        "Білки": "0,  Білки (0 % DV) "
    },
    "Фанта® середня": {
        "link": "/ua/uk-ua/product/200049.html",
        "name": "Фанта® середня",
        "description": "Всесвітньо відомий освіжаючий напій.",
        "Калорійність": "126 ккал/kcal,  Калорійність (6 % DV) ",
        "Жири": "0г/g,  Жири (0 % DV) ",
        "Вуглеводи": "31.6г/g,  Вуглеводи (12 % DV) ",
        "Білки": "0г/g,  Білки (0 % DV) ",
        "НЖК": "0г/g (0 % DV)",
        "Цукор": "31.6г/g (35 % DV)",
        "Сіль": "0.14г/g (2 % DV)",
        "Порція": "400мл/ml "
    },
    "Фанта® мала": {
        "link": "/ua/uk-ua/product/200050.html",
        "name": "Фанта® мала",
        "description": "Всесвітньо відомий освіжаючий напій.",
        "Калорійність": "0,  Калорійність (0 % DV) ",
        "Жири": "0,  Жири (0 % DV) ",
        "Вуглеводи": "0,  Вуглеводи (0 % DV) ",
        "Білки": "0,  Білки (0 % DV) "
    },
    "Спрайт® великий": {
        "link": "/ua/uk-ua/product/200158.html",
        "name": "Спрайт® великий",
        "description": "Всесвітньо відомий освіжаючий напій.",
        "Калорійність": "0,  Калорійність (0 % DV) ",
        "Жири": "0,  Жири (0 % DV) ",
        "Вуглеводи": "0,  Вуглеводи (0 % DV) ",
        "Білки": "0,  Білки (0 % DV) "
    },
    "Спрайт® середній": {
        "link": "/ua/uk-ua/product/200159.html",
        "name": "Спрайт® середній",
        "description": "Всесвітньо відомий освіжаючий напій.",
        "Калорійність": "0,  Калорійність (0 % DV) ",
        "Жири": "0,  Жири (0 % DV) ",
        "Вуглеводи": "0,  Вуглеводи (0 % DV) ",
        "Білки": "0,  Білки (0 % DV) "
    },
    "Спрайт® малий": {
        "link": "/ua/uk-ua/product/200160.html",
        "name": "Спрайт® малий",
        "description": "Всесвітньо відомий освіжаючий напій.",
        "Калорійність": "70 ккал/kcal,  Калорійність (4 % DV) ",
        "Жири": "0.0г/g,  Жири (0 % DV) ",
        "Вуглеводи": "17г/g,  Вуглеводи (6 % DV) ",
        "Білки": "0.0г/g,  Білки (0 % DV) ",
        "НЖК": "0.0г/g (0 % DV)",
        "Цукор": "17г/g (18 % DV)",
        "Сіль": "0.0г/g (0 % DV)",
        "Порція": "250мл/ml "
    },
    "Вода негазована велика": {
        "link": "/ua/uk-ua/product/7317.html",
        "name": "Вода негазована велика",
        "description": "",
        "Калорійність": "N/A ккал/kcal,  Калорійність (N/A % DV) ",
        "Жири": "N/Aг/g,  Жири (N/A % DV) ",
        "Вуглеводи": "N/Aг/g,  Вуглеводи (N/A % DV) ",
        "Білки": "N/Aг/g,  Білки (N/A % DV) ",
        "НЖК": "N/Aг/g (N/A % DV) N/Aг/g per100g ",
        "Цукор": "N/Aг/g (N/A % DV) N/Aг/g per100g ",
        "Сіль": "N/Aг/g (N/A % DV) N/Aг/g per100g ",
        "Порція": "500мл/ml (N/A % DV) N/Aмл/ml per100g "
    },
    "Вода негазована мала": {
        "link": "/ua/uk-ua/product/7319.html",
        "name": "Вода негазована мала",
        "description": "",
        "Калорійність": "0,  Калорійність (0 % DV) ",
        "Жири": "0,  Жири (0 % DV) ",
        "Вуглеводи": "0,  Вуглеводи (0 % DV) ",
        "Білки": "0,  Білки (0 % DV) "
    },
    "Вода газована велика": {
        "link": "/ua/uk-ua/product/7316.html",
        "name": "Вода газована велика",
        "description": "",
        "Калорійність": "0,  Калорійність (0 % DV) ",
        "Жири": "0,  Жири (0 % DV) ",
        "Вуглеводи": "0,  Вуглеводи (0 % DV) ",
        "Білки": "0,  Білки (0 % DV) "
    },
    "Вода газована мала": {
        "link": "/ua/uk-ua/product/7318.html",
        "name": "Вода газована мала",
        "description": "",
        "Калорійність": "0,  Калорійність (0 % DV) ",
        "Жири": "0,  Жири (0 % DV) ",
        "Вуглеводи": "0,  Вуглеводи (0 % DV) ",
        "Білки": "0,  Білки (0 % DV) "
    },
    "Сік «Галіція» яблучно-грушевий": {
        "link": "/ua/uk-ua/product/200361.html",
        "name": "Сік «Галіція» яблучно-грушевий",
        "description": "",
        "Калорійність": "80 ккал/kcal,  Калорійність (4 % DV) ",
        "Жири": "0.0г/g,  Жири (0 % DV) ",
        "Вуглеводи": "19г/g,  Вуглеводи (7 % DV) ",
        "Білки": "1.0г/g,  Білки (1 % DV) ",
        "НЖК": "0.0г/g (0 % DV)",
        "Цукор": "18г/g (19 % DV)",
        "Сіль": "1.0г/g (20 % DV)",
        "Порція": "200мл/ml (N/A % DV) N/Aмл/ml per100g "
    },
    "Сік «Галіція» яблучний": {
        "link": "/ua/uk-ua/product/7099.html",
        "name": "Сік «Галіція» яблучний",
        "description": "Новий натуральний сік прямого віджиму в меню МакДональдз® . В його складі лише стиглі фрукти — ніякого цукру, води чи консервантів.",
        "Калорійність": "0,  Калорійність (0 % DV) ",
        "Жири": "0,  Жири (0 % DV) ",
        "Вуглеводи": "0,  Вуглеводи (0 % DV) ",
        "Білки": "0,  Білки (0 % DV) "
    }
}